MANIFEST.in
README.md
setup.cfg
setup.py
django_jalali_date_3.egg-info/PKG-INFO
django_jalali_date_3.egg-info/SOURCES.txt
django_jalali_date_3.egg-info/dependency_links.txt
django_jalali_date_3.egg-info/not-zip-safe
django_jalali_date_3.egg-info/requires.txt
django_jalali_date_3.egg-info/top_level.txt
jalali_date/__init__.py
jalali_date/admin.py
jalali_date/fields.py
jalali_date/widgets.py
jalali_date/static/admin/jquery.ui.datepicker.jalali/default.htm
jalali_date/static/admin/jquery.ui.datepicker.jalali/scripts/calendar.all.js
jalali_date/static/admin/jquery.ui.datepicker.jalali/scripts/calendar.js
jalali_date/static/admin/jquery.ui.datepicker.jalali/scripts/jquery-1.10.2.min.js
jalali_date/static/admin/jquery.ui.datepicker.jalali/scripts/jquery-1.10.2.min.map
jalali_date/static/admin/jquery.ui.datepicker.jalali/scripts/jquery.ui.core.js
jalali_date/static/admin/jquery.ui.datepicker.jalali/scripts/jquery.ui.datepicker-cc-fa.js
jalali_date/static/admin/jquery.ui.datepicker.jalali/scripts/jquery.ui.datepicker-cc.js
jalali_date/static/admin/jquery.ui.datepicker.jalali/themes/base/jquery-ui.css
jalali_date/static/admin/jquery.ui.datepicker.jalali/themes/base/jquery-ui.min.css
jalali_date/static/admin/jquery.ui.datepicker.jalali/themes/base/jquery.ui.theme.css
jalali_date/static/admin/jquery.ui.datepicker.jalali/themes/base/images/animated-overlay.gif
jalali_date/static/admin/jquery.ui.datepicker.jalali/themes/base/images/ui-bg_flat_30_cccccc_40x100.png
jalali_date/static/admin/jquery.ui.datepicker.jalali/themes/base/images/ui-bg_flat_50_5c5c5c_40x100.png
jalali_date/static/admin/jquery.ui.datepicker.jalali/themes/base/images/ui-bg_glass_20_555555_1x400.png
jalali_date/static/admin/jquery.ui.datepicker.jalali/themes/base/images/ui-bg_glass_40_0078a3_1x400.png
jalali_date/static/admin/jquery.ui.datepicker.jalali/themes/base/images/ui-bg_glass_40_ffc73d_1x400.png
jalali_date/static/admin/jquery.ui.datepicker.jalali/themes/base/images/ui-bg_gloss-wave_25_333333_500x100.png
jalali_date/static/admin/jquery.ui.datepicker.jalali/themes/base/images/ui-bg_highlight-soft_80_eeeeee_1x100.png
jalali_date/static/admin/jquery.ui.datepicker.jalali/themes/base/images/ui-bg_inset-soft_25_000000_1x100.png
