Metadata-Version: 1.1
Name: django-jalali-date-3
Version: 0.2.0
Summary: Jalali Date support for user interface. Easy conversion of DateTimeFiled to JalaliDateTimeField within the admin site.
Home-page: http://github.com/a-roomana/django-jalali-date
Author: Arman Roomana
Author-email: roomana.arman@gmail.com
License: Python Software Foundation License
Download-URL: https://pypi.python.org/pypi/django-jalali-date/
Keywords: django jalali date
Platform: any
Classifier: Environment :: Web Environment
Classifier: Framework :: Django
Classifier: Intended Audience :: Developers
Classifier: Operating System :: OS Independent
Classifier: Programming Language :: Python
Classifier: Topic :: Software Development :: Libraries :: Application Frameworks
Classifier: Topic :: Software Development :: Libraries :: Python Modules
